LICENSE
MANIFEST.in
README.md
setup.py
cozy_indexer.egg-info/PKG-INFO
cozy_indexer.egg-info/SOURCES.txt
cozy_indexer.egg-info/dependency_links.txt
cozy_indexer.egg-info/entry_points.txt
cozy_indexer.egg-info/pbr.json
cozy_indexer.egg-info/requires.txt
cozy_indexer.egg-info/top_level.txt
cozyindexer/__init__.py
cozyindexer/app.py
cozyindexer/server.py
cozyindexer/settings.py
cozyindexer/urls.py
cozyindexer/handlers/__init__.py
cozyindexer/handlers/base.py
cozyindexer/handlers/indexer.py
cozyindexer/lib/__init__.py
cozyindexer/lib/indexer.py
cozyindexer/lib/stopwords.py
cozyindexer/lib/version.py